weclapp/__init__.py
weclapp/api.py
weclapp/app.py
weclapp/exception.py
weclapp/version.py
weclapp/bin/__init__.py
weclapp/bin/weclapp.py
weclapp/config/__init__.py
weclapp/config/config.py
weclapp/config/exceptions.py
weclapp/models/__init__.py
weclapp/models/base.py
weclapp/models/exceptions.py
weclapp/models/project.py
weclapp/models/task.py
weclapp/models/timeRecord.py
weclapp/modules/__init__.py
weclapp/modules/base.py
weclapp/modules/config.py
weclapp/modules/exceptions.py
weclapp/modules/project.py
weclapp/modules/upload.py
weclapp/parser/__init__.py
weclapp/parser/csvparser.py
weclapp/parser/exceptions.py
weclapp/parser/manage.py
weclapp/parser/parser.py
weclapp_cli-1.0.1.dist-info/LICENSE
weclapp_cli-1.0.1.dist-info/METADATA
weclapp_cli-1.0.1.dist-info/WHEEL
weclapp_cli-1.0.1.dist-info/entry_points.txt
weclapp_cli-1.0.1.dist-info/top_level.txt
weclapp_cli-1.0.1.dist-info/RECORD
