Metadata-Version: 2.1
Name: weclapp-cli
Version: 1.0.1
Summary: A small cli for uploading time records via a CSV file
Home-page: https://shaoran.github.io/weclapp-cli/
Author: Pablo Yanez Trujillo
License: UNKNOWN
Project-URL: Homepage, https://shaoran.github.io/weclapp-cli/
Project-URL: Bug Reports, https://github.com/shaoran/weclapp-cli/issues
Project-URL: Source, https://github.com/shaoran/weclapp-cli
Keywords: weclapp time records uploader
Platform: UNKNOWN
Classifier: Development Status :: 5 - Production/Stable
Classifier: Intended Audience :: End Users/Desktop
Classifier: Topic :: Office/Business
Classifier: License :: OSI Approved :: GNU General Public License v2 (GPLv2)
Classifier: Programming Language :: Python :: 3 :: Only
Requires-Python: >=3
Requires-Dist: PyYAML
Requires-Dist: colorama
Requires-Dist: coloredlogs
Requires-Dist: python-dateutil
